odoo/addons/base_import_pdf_by_template_account/README.rst
odoo/addons/base_import_pdf_by_template_account/__init__.py
odoo/addons/base_import_pdf_by_template_account/__manifest__.py
odoo/addons/base_import_pdf_by_template_account/demo/base_import_pdf_template.xml
odoo/addons/base_import_pdf_by_template_account/i18n/base_import_pdf_by_template_account.pot
odoo/addons/base_import_pdf_by_template_account/i18n/es.po
odoo/addons/base_import_pdf_by_template_account/i18n/it.po
odoo/addons/base_import_pdf_by_template_account/models/__init__.py
odoo/addons/base_import_pdf_by_template_account/models/account_move.py
odoo/addons/base_import_pdf_by_template_account/readme/CONTRIBUTORS.md
odoo/addons/base_import_pdf_by_template_account/readme/DESCRIPTION.md
odoo/addons/base_import_pdf_by_template_account/security/ir.model.access.csv
odoo/addons/base_import_pdf_by_template_account/security/security.xml
odoo/addons/base_import_pdf_by_template_account/static/description/icon.png
odoo/addons/base_import_pdf_by_template_account/static/description/index.html
odoo/addons/base_import_pdf_by_template_account/tests/__init__.py
odoo/addons/base_import_pdf_by_template_account/tests/test_base_import_pdf_by_template_account.py
odoo/addons/base_import_pdf_by_template_account/tests/data/account_invoice_tecnativa.pdf
odoo/addons/base_import_pdf_by_template_account/views/base_import_pdf_template_views.xml
odoo_addon_base_import_pdf_by_template_account-17.0.1.0.5.dist-info/METADATA
odoo_addon_base_import_pdf_by_template_account-17.0.1.0.5.dist-info/WHEEL
odoo_addon_base_import_pdf_by_template_account-17.0.1.0.5.dist-info/top_level.txt
odoo_addon_base_import_pdf_by_template_account-17.0.1.0.5.dist-info/RECORD
