Metadata-Version: 2.1
Name: odoo-addon-base_import_pdf_by_template_account
Version: 17.0.1.0.5
Requires-Python: >=3.10
Requires-Dist: odoo-addon-base_import_pdf_by_template>=17.0dev,<17.1dev
Requires-Dist: odoo>=17.0a,<17.1dev
Summary: Base Import Pdf by Template Account
Home-page: https://github.com/OCA/edi
License: AGPL-3
Author: Tecnativa, Odoo Community Association (OCA)
Author-email: support@odoo-community.org
Classifier: Programming Language :: Python
Classifier: Framework :: Odoo
Classifier: Framework :: Odoo :: 17.0
Classifier: License :: OSI Approved :: GNU Affero General Public License v3
